setup.py
IndustryCitics/IndustryCitics.py
IndustryCitics/__init__.py
IndustryCitics/pk_debug.py
IndustryCitics.egg-info/PKG-INFO
IndustryCitics.egg-info/SOURCES.txt
IndustryCitics.egg-info/dependency_links.txt
IndustryCitics.egg-info/top_level.txt