Metadata-Version: 2.1
Name: IndustryCitics
Version: 0.0.16
Summary: AShare analysis at CITICS industry level1
Author: Xi
